[
  {
    "ID": "Weapon_LRM_ALRM15_0-STOCK",
    "Weight": 0
  },
  {
    "ID": "Weapon_LRM_ALRM15_1-Delta",
    "Weight": 2
  },
  {
    "ID": "Weapon_LRM_ALRM15_1-LongFire",
    "Weight": 2
  },
  {
    "ID": "Weapon_LRM_ALRM15_1-Telos",
    "Weight": 2
  },
  {
    "ID": "Weapon_LRM_ALRM15_2-Delta",
    "Weight": 2
  },
  {
    "ID": "Weapon_LRM_ALRM15_2-LongFire",
    "Weight": 2
  },
  {
    "ID": "Weapon_LRM_ALRM15_2-Telos",
    "Weight": 2
  },
  {
    "ID": "Weapon_LRM_ALRM15_2-Zeus",
    "Weight": 2
  },
  {
    "ID": "Weapon_LRM_ALRM15_3-Zeus",
    "Weight": 2
  }
]